{"name":"build-javascript","namedChunkGroups":{"app":{"name":"app","assets":[{"name":"webpack-runtime-fa0b38a8939b45fb543a.js","size":4883},{"name":"framework-a65d481e5d107d6a4887.js","size":140994},{"name":"app-279b8105af999a7f7d3b.js","size":68575}],"filteredAssets":0,"assetsSize":214452,"filteredAuxiliaryAssets":3,"auxiliaryAssetsSize":619089},"component---src-pages-404-tsx":{"name":"component---src-pages-404-tsx","assets":[{"name":"styles.2437d5e69e177f87d0a9.css","size":2985},{"name":"2cca2479-962c908097bc0c54e62e.js","size":1592},{"name":"commons-bb6f29a943792a738ada.js","size":57783},{"name":"component---src-pages-404-tsx-f0339b50b3e56d936662.js","size":739}],"filteredAssets":0,"assetsSize":63099,"filteredAuxiliaryAssets":3,"auxiliaryAssetsSize":730384},"component---src-pages-entry-markdown-remark-frontmatter-slug-tsx":{"name":"component---src-pages-entry-markdown-remark-frontmatter-slug-tsx","assets":[{"name":"styles.2437d5e69e177f87d0a9.css","size":2985},{"name":"2cca2479-962c908097bc0c54e62e.js","size":1592},{"name":"commons-bb6f29a943792a738ada.js","size":57783},{"name":"component---src-pages-entry-markdown-remark-frontmatter-slug-tsx-97c98ec7b8d7a1f5010a.js","size":369948}],"filteredAssets":0,"assetsSize":432308,"filteredAuxiliaryAssets":3,"auxiliaryAssetsSize":2582682},"component---src-pages-index-tsx":{"name":"component---src-pages-index-tsx","assets":[{"name":"styles.2437d5e69e177f87d0a9.css","size":2985},{"name":"2cca2479-962c908097bc0c54e62e.js","size":1592},{"name":"commons-bb6f29a943792a738ada.js","size":57783},{"name":"component---src-pages-index-tsx-19696865b66367a25a1e.js","size":1598}],"filteredAssets":0,"assetsSize":63958,"filteredAuxiliaryAssets":3,"auxiliaryAssetsSize":734058}},"assetsByChunkName":{"app":["webpack-runtime-fa0b38a8939b45fb543a.js","framework-a65d481e5d107d6a4887.js","app-279b8105af999a7f7d3b.js"],"component---src-pages-404-tsx":["styles.2437d5e69e177f87d0a9.css","2cca2479-962c908097bc0c54e62e.js","commons-bb6f29a943792a738ada.js","component---src-pages-404-tsx-f0339b50b3e56d936662.js"],"component---src-pages-entry-markdown-remark-frontmatter-slug-tsx":["styles.2437d5e69e177f87d0a9.css","2cca2479-962c908097bc0c54e62e.js","commons-bb6f29a943792a738ada.js","component---src-pages-entry-markdown-remark-frontmatter-slug-tsx-97c98ec7b8d7a1f5010a.js"],"component---src-pages-index-tsx":["styles.2437d5e69e177f87d0a9.css","2cca2479-962c908097bc0c54e62e.js","commons-bb6f29a943792a738ada.js","component---src-pages-index-tsx-19696865b66367a25a1e.js"]},"childAssetsByChunkName":{}}